[{"meta":{"id":"precede","uuid":"5045ee2b-d6fb-4e00-ba72-97d5b1add23c","lang":"en","src":"spanish","section":"alpha","stems":["precede","preceded","preceding","precedes"],"offensive":false},"hwi":{"hw":"precede","prs":[{"mw":"pri\u02c8si\u02d0d","sound":{"audio":"preced01"}}]},"fl":"verb","ins":[{"ifc":"-ceded","if":"preceded"},{"ifc":"-ceding","if":"preceding"}],"def":[{"sseq":[[["sense",{"dt":[["text","{bc}preceder a"]]}]]]}],"shortdef":["preceder a"]}][{"meta":{"id":"anticipate","uuid":"581cdd42-07bd-481d-8359-0ebbad119521","lang":"en","src":"spanish","section":"alpha","stems":["anticipate","anticipated","anticipating","anticipates","anticipatable","anticipator","anticipators"],"offensive":false},"hwi":{"hw":"anticipate","prs":[{"mw":"\u00e6n\u02c8t\u026as\u0259\u02ccpe\u026at","sound":{"audio":"antici02"}}]},"fl":"transitive verb","ins":[{"ifc":"-pated","if":"anticipated"},{"ifc":"-pating","if":"anticipating"}],"def":[{"sseq":[[["sense",{"sn":"1","dt":[["text","{sx|foresee||} {bc}{a_link|anticipar}, {a_link|prever}"]]}]],[["sense",{"sn":"2","dt":[["text","{sx|expect||} {bc}{a_link|esperar}, {a_link|contar con}"]]}]]]}],"shortdef":["foresee : anticipar, prever","expect : esperar, contar con"]}]