[{"meta":{"id":"found:1","uuid":"db1f57e9-7bdf-4836-8b62-d97c6851451c","lang":"en","src":"spanish","section":"alpha","stems":["found","find"],"offensive":false},"hom":1,"hwi":{"hw":"found"},"xrs":[[{"xrt":"find","xref":"find"}]],"shortdef":[]},{"meta":{"id":"found:2","uuid":"024e29ba-2fe6-4eb5-989d-a8b87c0fa493","lang":"en","src":"spanish","section":"alpha","stems":["found","founded","founding","founds"],"offensive":false},"hom":2,"hwi":{"hw":"found","prs":[{"mw":"\u02c8fa\u028and"}]},"fl":"transitive verb","def":[{"sseq":[[["sense",{"dt":[["text","{bc}{a_link|fundar}, {a_link|establecer}"]]}]]]}],"shortdef":["fundar, establecer"]},{"meta":{"id":"find:1","uuid":"aabee92b-f090-45ea-be6d-e068768822a9","lang":"en","src":"spanish","section":"alpha","stems":["find","found","finding","finds","findable","find fault","to find fault","to find favor\/approval","to find approval","to find favor","to find oneself","to find one\u0027s way","to find ones way","to find out"],"offensive":false},"hom":1,"hwi":{"hw":"find","prs":[{"mw":"\u02c8fa\u026and","sound":{"audio":"find0001"}}]},"fl":"transitive verb","ins":[{"if":"found","prs":[{"mw":"\u02c8fa\u028and","sound":{"audio":"find0002"}}]},{"if":"finding"}],"def":[{"sseq":[[["sense",{"sn":"1","dt":[["text","{sx|locate||} {bc}{a_link|encontrar} "],["vis",[{"t":"I can\u0027t find it","tr":"no lo encuentro"},{"t":"he was nowhere to be found","tr":"no se lo encontraba por ninguna parte"}]]]}]],[["sense",{"sn":"2","dt":[["text","{sx|chance upon||} {bc}{a_link|encontrar} (por casualidad) "],["vis",[{"t":"I found a dollar","tr":"encontr\u00e9 un d\u00f3lar"}]]]}]],[["sense",{"sn":"3","dt":[["text","{sx|learn||} {bc}{a_link|encontrar}, {a_link|descubrir} "],["vis",[{"t":"to find the answer","tr":"encontrar la soluci\u00f3n"},{"t":"we found that \u2026","tr":"descubrimos que \u2026"}]]]}]],[["sense",{"sn":"4","dt":[["text","{sx|get||} {bc}{a_link|encontrar}, {a_link|obtener} "],["vis",[{"t":"to find the time to do something","tr":"encontrar el tiempo para hacer algo"},{"t":"to find satisfaction in","tr":"obtener satisfacci\u00f3n de"}]]]}]],[["sense",{"sn":"5","dt":[["text","{sx|perceive||} {bc}{a_link|encontrar} "],["vis",[{"t":"I find it strange\/difficult","tr":"lo encuentro raro\/dif\u00edcil, me resulta raro\/dif\u00edcil"}]]]}]],[["sense",{"sn":"6","dt":[["text","{sx|declare||} {bc}{a_link|declarar}, {a_link|hallar} "],["vis",[{"t":"they found him guilty","tr":"lo declararon culpable"}]]]}]],[["sense",{"sn":"7","vrs":[{"va":"to find fault"}],"dt":[["text","{bc}{a_link|criticar}"]]}]],[["sense",{"sn":"8","vrs":[{"va":"to find favor\/approval"}],"dt":[["text","{bc}ser bien recibido"]]}]],[["sense",{"sn":"9","vrs":[{"va":"to find oneself"}],"dt":[["vis",[{"t":"she found herself in an unfamiliar place","tr":"se encontr\u00f3 en un lugar desconocido"},{"t":"he found himself in a bad situation","tr":"se vio en apuros"},{"t":"I found myself thinking about her","tr":"me di cuenta de que estaba pensando en ella"}]]]}]],[["sense",{"sn":"10","vrs":[{"va":"to find oneself"}],"dt":[["vis",[{"t":"he left to find himself","tr":"se fue para encontrarse a s\u00ed mismo"}]]]}]],[["sense",{"sn":"11","vrs":[{"va":"to find one\u0027s way"}],"dt":[["text","{bc}encontrar el camino, {a_link|orientarse}"]]}]],[["sense",{"sn":"12","vrs":[{"va":"to find out"}],"dt":[["text","{bc}{a_link|descubrir}, {a_link|averiguar}"]]}]]]}],"shortdef":["locate : encontrar","chance upon : encontrar (por casualidad)","learn : encontrar, descubrir"]},{"meta":{"id":"find out","uuid":"5ab42231-ac5c-4195-88fa-6d86b16e5eed","lang":"en","src":"spanish","section":"alpha","stems":["find out","found out","finding out","finds out"],"offensive":false},"hwi":{"hw":"find out"},"fl":"transitive verb","def":[{"sseq":[[["sense",{"dt":[["text","{sx|discover||} {bc}{a_link|descubrir}, {a_link|averiguar}"]]}]]]},{"vd":"intransitive verb","sseq":[[["sense",{"dt":[["text","{sx|learn||} {bc}{a_link|enterarse}"]]}]]]}],"shortdef":["discover : descubrir, averiguar","learn : enterarse"]}][{"meta":{"id":"acquire","uuid":"fbd1c80a-945e-485c-ac97-345a097b3f8c","lang":"en","src":"spanish","section":"alpha","stems":["acquire","acquired","acquiring","acquires"],"offensive":false},"hwi":{"hw":"acquire","prs":[{"mw":"\u0259\u02c8kwa\u026ar","sound":{"audio":"acquir02"}}]},"fl":"transitive verb","ins":[{"ifc":"-quired","if":"acquired"},{"ifc":"-quiring","if":"acquiring"}],"def":[{"sseq":[[["sense",{"dt":[["text","{bc}{a_link|adquirir}, {a_link|obtener}"]]}]]]}],"shortdef":["adquirir, obtener"]}][{"meta":{"id":"discover","uuid":"d9135f11-26a0-4a01-a6a2-f5300e6b9298","lang":"en","src":"spanish","section":"alpha","stems":["discover","discovered","discovering","discovers","discoverable","discoverer","discoverers"],"offensive":false},"hwi":{"hw":"discover","prs":[{"mw":"d\u026as\u02c8k\u028cv\u0259r","sound":{"audio":"discov01"}}]},"fl":"transitive verb","def":[{"sseq":[[["sense",{"dt":[["text","{bc}{a_link|descubrir}"]]}]]]}],"shortdef":["descubrir"]}]