[{"meta":{"id":"February","uuid":"be93c610-20b5-40e7-995c-773d4601e604","lang":"en","src":"spanish","section":"alpha","stems":["february","februaries","februarys"],"offensive":false},"hwi":{"hw":"February","prs":[{"mw":"\u02c8f\u025bbj\u028a\u02ccri","sound":{"audio":"februa02"}},{"mw":"\u02c8f\u025bb\u028a-","sound":{"audio":"februa01"}},{"mw":"\u02c8f\u025bbr\u028a-"}]},"fl":"noun","def":[{"sseq":[[["sense",{"dt":[["text","{bc}{a_link|febrero} "],["gl","masculine"],["vis",[{"t":"they arrived on the 21st of February, they arrived on February 21st","tr":"llegaron el 21 de febrero"}]]]}]]]}],"shortdef":["febrero"]}]